vacancy_predictor/__init__.py
vacancy_predictor/main.py
vacancy_predictor/core/__init__.py
vacancy_predictor/core/batch_processor.py
vacancy_predictor/core/config.py
vacancy_predictor/core/data_leakage_detector.py
vacancy_predictor/core/data_processor.py
vacancy_predictor/core/enhanced_safe_feature_extractor.py
vacancy_predictor/core/feature_extractor.py
vacancy_predictor/core/file_parser.py
vacancy_predictor/core/enhanced_ml/__init__.py
vacancy_predictor/core/enhanced_ml/model_configuration_tab.py
vacancy_predictor/core/enhanced_ml/multi_model_processor.py
vacancy_predictor/gui/__init__.py
vacancy_predictor/gui/app.py
vacancy_predictor/gui/tabs/__init__.py
vacancy_predictor/gui/tabs/advanced_ml_tab.py
vacancy_predictor/gui/tabs/batch_processor_tab.py
vacancy_predictor/gui/tabs/dump_processor_tab.py
vacancy_predictor/gui/tabs/kfold_visualization.py
vacancy_predictor/gui/tabs/multi_model_tab.py
vacancy_predictor/gui/tabs/predictor_gui.py
vacancy_predictor/gui/tabs/test_predict.py
vacancy_predictor/gui/tabs/vacancy_predictor_simple.py
vacancy_predictor/utils/__init__.py
vacancy_predictor/utils/file_handlers.py
vacancy_predictor/utils/validators.py
freedynamics_simaf-2.7.9.dist-info/METADATA
freedynamics_simaf-2.7.9.dist-info/WHEEL
freedynamics_simaf-2.7.9.dist-info/entry_points.txt
freedynamics_simaf-2.7.9.dist-info/top_level.txt
freedynamics_simaf-2.7.9.dist-info/RECORD
